setup.py
django_mailify.egg-info/PKG-INFO
django_mailify.egg-info/SOURCES.txt
django_mailify.egg-info/dependency_links.txt
django_mailify.egg-info/not-zip-safe
django_mailify.egg-info/top_level.txt
mailify/__init__.py
mailify/admin.py
mailify/fields.py
mailify/models.py
mailify/receivers.py
mailify/settings.py
mailify/signals.py
mailify/tasks.py
mailify/management/__init__.py
mailify/management/commands/__init__.py
mailify/management/commands/send_deferred.py