Metadata-Version: 1.0
Name: django-mailify
Version: 0.1.0alpha2
Summary: Enhance the builtin Django mail functionality to include task queueing or deferment.
Home-page: https://keithio.github.com/django-mailify
Author: Keith Hall
Author-email: code@keith.io
License: UNKNOWN
Platform: UNKNOWN
Classifier: Environment :: Web Environment
Classifier: Framework :: Django
Classifier: License :: OSI Approved :: MIT License
Classifier: Operating System :: OS Independent
Classifier: Programming Language :: Python
